setup.py
cosmos/__init__.py
cosmos.egg-info/PKG-INFO
cosmos.egg-info/SOURCES.txt
cosmos.egg-info/dependency_links.txt
cosmos.egg-info/entry_points.txt
cosmos.egg-info/requires.txt
cosmos.egg-info/top_level.txt
cosmos/admin/__init__.py
cosmos/admin/commands.py
cosmos/admin/createproject.py
cosmos/admin/publish.py
cosmos/admin/samples/__init__.py
cosmos/admin/samples/adminpaneldef.py
cosmos/admin/samples/angularbasicdef.py
cosmos/admin/samples/angulardef.py
cosmos/admin/samples/barebonedef.py
cosmos/admin/samples/simpledef.py
cosmos/auth/__init__.py
cosmos/auth/oauth2.py
cosmos/bees/__init__.py
cosmos/bees/celery/__init__.py
cosmos/bees/celery/workflow.py
cosmos/certmgr/__init__.py
cosmos/certmgr/certfactory.py
cosmos/common/__init__.py
cosmos/common/constants.py
cosmos/datamonitor/__init__.py
cosmos/datamonitor/monitor.py
cosmos/dataservice/__init__.py
cosmos/dataservice/objectservice.py
cosmos/msgq/__init__.py
cosmos/msgq/amazon.py
cosmos/msgq/azure.py
cosmos/msgq/rabbitmq.py
cosmos/processors/__init__.py
cosmos/rbac/__init__.py
cosmos/rbac/cache.py
cosmos/rbac/object.py
cosmos/rbac/service.py
cosmos/schema/__init__.py
cosmos/schema/object.py
cosmos/service/__init__.py
cosmos/service/appservice.py
cosmos/service/auth.py
cosmos/service/certservice.py
cosmos/service/constants.py
cosmos/service/formview.py
cosmos/service/gridfsservice.py
cosmos/service/importexport.py
cosmos/service/oauth2service.py
cosmos/service/requesthandler.py
cosmos/service/search.py
cosmos/service/servicehandler.py
cosmos/service/servicemain.py
cosmos/service/utils.py
cosmos/util/__init__.py
test/__init__.py