Metadata-Version: 1.1
Name: cosmos
Version: 0.1.93.3
Summary: Thin server application framework
Home-page: http://cosmosframework.com
Author: Maruf Maniruzzaman
Author-email: marufm@cosmosframework.com
License: MIT License
Platform: UNKNOWN
Classifier: Development Status :: 3 - Alpha
Classifier: Intended Audience :: Developers
Classifier: Topic :: Software Development :: Libraries :: Application Frameworks
Classifier: License :: OSI Approved :: MIT License
Classifier: Programming Language :: Python :: 2.7
Classifier: Programming Language :: Python :: 3.5
Classifier: Programming Language :: JavaScript
